pdm_polylith_bricks/polylith/building/__init__.py
pdm_polylith_bricks/polylith/building/core.py
pdm_polylith_bricks/polylith/building/paths.py
pdm_polylith_bricks/polylith/configuration/__init__.py
pdm_polylith_bricks/polylith/configuration/core.py
pdm_polylith_bricks/polylith/parsing/__init__.py
pdm_polylith_bricks/polylith/parsing/core.py
pdm_polylith_bricks/polylith/parsing/rewrite.py
pdm_polylith_bricks/polylith/pdm/__init__.py
pdm_polylith_bricks/polylith/pdm/core.py
pdm_polylith_bricks/polylith/pdm/hooks/__init__.py
pdm_polylith_bricks/polylith/pdm/hooks/bricks.py
pdm_polylith_bricks/polylith/pdm/hooks/workspace.py
pdm_polylith_bricks/polylith/pdm_project_hooks/__init__.py
pdm_polylith_bricks/polylith/pdm_project_hooks/core.py
pdm_polylith_bricks/polylith/repo/__init__.py
pdm_polylith_bricks/polylith/repo/get.py
pdm_polylith_bricks/polylith/repo/repo.py
pdm_polylith_bricks/polylith/toml/__init__.py
pdm_polylith_bricks/polylith/toml/core.py
pdm_polylith_bricks-1.3.3.dist-info/METADATA
pdm_polylith_bricks-1.3.3.dist-info/WHEEL
pdm_polylith_bricks-1.3.3.dist-info/entry_points.txt
pdm_polylith_bricks-1.3.3.dist-info/RECORD
